nbtransom/__init__.py
nbtransom/nbtransom.py
nbtransom-1.0.1.dist-info/DESCRIPTION.rst
nbtransom-1.0.1.dist-info/METADATA
nbtransom-1.0.1.dist-info/RECORD
nbtransom-1.0.1.dist-info/WHEEL
nbtransom-1.0.1.dist-info/metadata.json
nbtransom-1.0.1.dist-info/top_level.txt
