Metadata-Version: 2.0
Name: nbtransom
Version: 1.0.1
Summary: Machines and people collaborating together through Jupyter notebooks.
Home-page: http://github.com/ceteri/nbtransom
Author: Paco Nathan
Author-email: ceteri@gmail.com
License: Apache License 2.0
Keywords: human-in-the-loop,active learning,collaborative documents,jupyter notebook,pipelines,machine learning
Platform: UNKNOWN
Classifier: Development Status :: 5 - Production/Stable
Classifier: Framework :: Jupyter
Classifier: Intended Audience :: Developers
Classifier: Intended Audience :: Information Technology
Classifier: Intended Audience :: Science/Research
Classifier: License :: OSI Approved :: Apache Software License
Classifier: Operating System :: OS Independent
Classifier: Programming Language :: Python :: 3
Classifier: Topic :: Scientific/Engineering :: Artificial Intelligence
Classifier: Topic :: Scientific/Engineering :: Human Machine Interfaces
Classifier: Topic :: Scientific/Engineering :: Information Analysis
Requires-Dist: nbformat
Requires-Dist: pandas
